CONTRIBUTING.rst
HISTORY.rst
LICENSE
MANIFEST.in
README.rst
setup.cfg
setup.py
django_nonmodel_admin/__init__.py
django_nonmodel_admin/admin.py
django_nonmodel_admin.egg-info/PKG-INFO
django_nonmodel_admin.egg-info/SOURCES.txt
django_nonmodel_admin.egg-info/dependency_links.txt
django_nonmodel_admin.egg-info/not-zip-safe
django_nonmodel_admin.egg-info/top_level.txt
tests/__init__.py
tests/test_django_nonmodel_admin.py