Metadata-Version: 2.1
Name: django-nonmodel-admin
Version: 0.1.1
Summary: Allows to add sections to django admin which are not tied to any model. They can render some template for example.
Home-page: https://github.com/pawnhearts/django_nonmodel_admin
Author: robot naoborot
Author-email: robotnaoborot@gmail.com
License: MIT license
Keywords: django_nonmodel_admin
Platform: UNKNOWN
Classifier: Development Status :: 2 - Pre-Alpha
Classifier: Intended Audience :: Developers
Classifier: License :: OSI Approved :: MIT License
Classifier: Natural Language :: English
Classifier: Programming Language :: Python :: 3
Classifier: Programming Language :: Python :: 3.6
Classifier: Programming Language :: Python :: 3.7
Classifier: Programming Language :: Python :: 3.8
Requires-Python: >=3.6
License-File: LICENSE
